[
  {
    "time": "",
    "player1": "Sinner J.",
    "player2": "Struff J.",
    "seed1": 1,
    "seed2": null,
    "book_odds_home": 1.05,
    "book_odds_away": 11.18,
    "tournament": "Wimbledon",
    "surface": "grass",
    "category": "GS",
    "tour": "ATP",
    "name1": "Jannik\u00a0Sinner",
    "name2": "Jan\u00a0Lennard\u00a0Struff",
    "r1": {
      "elo_rank": 1,
      "age": 24.7,
      "elo": 2319.8,
      "hElo": 2263.2,
      "cElo": 2215.7,
      "gElo": 2088.3,
      "atp_rank": 1,
      "surface_score": 4
    },
    "r2": {
      "elo_rank": 117,
      "age": 36.1,
      "elo": 1694.2,
      "hElo": 1634.2,
      "cElo": 1659.3,
      "gElo": 1623.1,
      "atp_rank": 74,
      "surface_score": 3
    },
    "c_elo1": 2215.7,
    "h_elo1": 2263.2,
    "c_elo2": 1659.3,
    "h_elo2": 1634.2,
    "ss1": 7,
    "ss2": 4,
    "prob1": 0.9357102984910504,
    "odds1": 1.07,
    "odds2": 15.55,
    "edge1": -0.0167,
    "edge2": -0.0252,
    "court_cpi": 37,
    "elo_found": true,
    "error": null,
    "status": "upcoming"
  },
  {
    "time": "",
    "player1": "Lehecka J.",
    "player2": "Zverev A.",
    "seed1": 13,
    "seed2": 2,
    "book_odds_home": 3.43,
    "book_odds_away": 1.32,
    "tournament": "Wimbledon",
    "surface": "grass",
    "category": "GS",
    "tour": "ATP",
    "name1": "Jiri\u00a0Lehecka",
    "name2": "Alexander\u00a0Zverev",
    "r1": {
      "elo_rank": 17,
      "age": 24.5,
      "elo": 1921.6,
      "hElo": 1882.1,
      "cElo": 1825.5,
      "gElo": 1798.4,
      "atp_rank": 14,
      "surface_score": 4
    },
    "r2": {
      "elo_rank": 3,
      "age": 29.1,
      "elo": 2099.7,
      "hElo": 2041.5,
      "cElo": 2051.1,
      "gElo": 1913.6,
      "atp_rank": 3,
      "surface_score": 3
    },
    "c_elo1": 1825.5,
    "h_elo1": 1882.1,
    "c_elo2": 2051.1,
    "h_elo2": 2041.5,
    "ss1": 7,
    "ss2": 5,
    "prob1": 0.3400335958696014,
    "odds1": 2.94,
    "odds2": 1.52,
    "edge1": 0.0485,
    "edge2": -0.0976,
    "court_cpi": 37,
    "elo_found": true,
    "error": null,
    "status": "upcoming"
  },
  {
    "time": "",
    "player1": "Auger Aliassime F.",
    "player2": "Djokovic N.",
    "seed1": 3,
    "seed2": 7,
    "book_odds_home": 2.39,
    "book_odds_away": 1.58,
    "tournament": "Wimbledon",
    "surface": "grass",
    "category": "GS",
    "tour": "ATP",
    "name1": "Felix\u00a0Auger\u00a0Aliassime",
    "name2": "Novak\u00a0Djokovic",
    "r1": {
      "elo_rank": 11,
      "age": 25.8,
      "elo": 1957.9,
      "hElo": 1932.2,
      "cElo": 1863.9,
      "gElo": 1789.1,
      "atp_rank": 4,
      "surface_score": 4
    },
    "r2": {
      "elo_rank": 4,
      "age": 39.0,
      "elo": 2059.3,
      "hElo": 2021.7,
      "cElo": 1959.2,
      "gElo": 1924.9,
      "atp_rank": 8,
      "surface_score": 4
    },
    "c_elo1": 1863.9,
    "h_elo1": 1932.2,
    "c_elo2": 1959.2,
    "h_elo2": 2021.7,
    "ss1": 7,
    "ss2": 7,
    "prob1": 0.31394765978543604,
    "odds1": 3.19,
    "odds2": 1.46,
    "edge1": -0.1045,
    "edge2": 0.0531,
    "court_cpi": 37,
    "elo_found": true,
    "error": null,
    "status": "upcoming"
  },
  {
    "time": "",
    "player1": "Pegula J.",
    "player2": "Gauff C.",
    "seed1": 4,
    "seed2": 7,
    "book_odds_home": 1.56,
    "book_odds_away": 2.43,
    "tournament": "Wimbledon",
    "surface": "grass",
    "category": "GS",
    "tour": "WTA",
    "name1": "Jessica\u00a0Pegula",
    "name2": "Coco\u00a0Gauff",
    "r1": {
      "elo_rank": 3,
      "age": 32.3,
      "elo": 2096.5,
      "hElo": 2058.0,
      "cElo": 1941.4,
      "gElo": 1903.4,
      "atp_rank": 4,
      "surface_score": 5
    },
    "r2": {
      "elo_rank": 5,
      "age": 22.2,
      "elo": 2071.2,
      "hElo": 2034.7,
      "cElo": 2018.4,
      "gElo": 1822.8,
      "atp_rank": 7,
      "surface_score": 3
    },
    "c_elo1": 1941.4,
    "h_elo1": 2058.0,
    "c_elo2": 2018.4,
    "h_elo2": 2034.7,
    "ss1": 8,
    "ss2": 6,
    "prob1": 0.6139557593128276,
    "odds1": 1.63,
    "odds2": 2.59,
    "edge1": -0.0271,
    "edge2": -0.0255,
    "court_cpi": 37,
    "elo_found": true,
    "error": null,
    "status": "upcoming"
  },
  {
    "time": "",
    "player1": "Osaka N.",
    "player2": "Muchova K.",
    "seed1": 14,
    "seed2": 10,
    "book_odds_home": 1.7,
    "book_odds_away": 2.15,
    "tournament": "Wimbledon",
    "surface": "grass",
    "category": "GS",
    "tour": "WTA",
    "name1": "Naomi\u00a0Osaka",
    "name2": "Karolina\u00a0Muchova",
    "r1": {
      "elo_rank": 12,
      "age": 28.6,
      "elo": 1987.4,
      "hElo": 1921.5,
      "cElo": 1886.1,
      "gElo": 1793.0,
      "atp_rank": 14,
      "surface_score": 3
    },
    "r2": {
      "elo_rank": 7,
      "age": 29.8,
      "elo": 2066.1,
      "hElo": 2034.1,
      "cElo": 1892.5,
      "gElo": 1851.7,
      "atp_rank": 9,
      "surface_score": 5
    },
    "c_elo1": 1886.1,
    "h_elo1": 1921.5,
    "c_elo2": 1892.5,
    "h_elo2": 2034.1,
    "ss1": 7,
    "ss2": 8,
    "prob1": 0.41631862213708526,
    "odds1": 2.4,
    "odds2": 1.71,
    "edge1": -0.1719,
    "edge2": 0.1186,
    "court_cpi": 37,
    "elo_found": true,
    "error": null,
    "status": "upcoming"
  }
]