[
  {
    "time": "13:10",
    "player1": "Collignon R.",
    "player2": "Bautista-Agut R.",
    "seed1": 1,
    "seed2": 5,
    "book_odds_home": 1.49,
    "book_odds_away": 2.55,
    "tournament": "Halle",
    "surface": "grass",
    "category": "A500",
    "tour": "ATP"
  },
  {
    "time": "13:10",
    "player1": "Basilashvili N.",
    "player2": "Sonego L.",
    "seed1": 6,
    "seed2": 3,
    "book_odds_home": 2.49,
    "book_odds_away": 1.5,
    "tournament": "Halle",
    "surface": "grass",
    "category": "A500",
    "tour": "ATP"
  },
  {
    "time": "",
    "player1": "Landaluce M.",
    "player2": "Gentzsch T.",
    "seed1": 2,
    "seed2": 8,
    "book_odds_home": 1.3,
    "book_odds_away": 3.39,
    "tournament": "Halle",
    "surface": "grass",
    "category": "A500",
    "tour": "ATP"
  },
  {
    "time": "",
    "player1": "Bellucci M.",
    "player2": "Bolt A.",
    "seed1": 4,
    "seed2": 7,
    "book_odds_home": 1.54,
    "book_odds_away": 2.4,
    "tournament": "Halle",
    "surface": "grass",
    "category": "A500",
    "tour": "ATP"
  },
  {
    "time": "13:05",
    "player1": "Damm M.",
    "player2": "Svajda Z.",
    "seed1": null,
    "seed2": 1,
    "book_odds_home": 2.13,
    "book_odds_away": 1.67,
    "tournament": "Queen's Club",
    "surface": "grass",
    "category": "A500",
    "tour": "ATP"
  },
  {
    "time": "13:10",
    "player1": "Wendelken H.",
    "player2": "Vukic A.",
    "seed1": null,
    "seed2": null,
    "book_odds_home": 2.35,
    "book_odds_away": 1.56,
    "tournament": "Queen's Club",
    "surface": "grass",
    "category": "A500",
    "tour": "ATP"
  },
  {
    "time": "",
    "player1": "Hijikata R.",
    "player2": "Giron M.",
    "seed1": null,
    "seed2": 6,
    "book_odds_home": 2.09,
    "book_odds_away": 1.7,
    "tournament": "Queen's Club",
    "surface": "grass",
    "category": "A500",
    "tour": "ATP"
  },
  {
    "time": "",
    "player1": "Kovacevic A.",
    "player2": "Mpetshi Perricard G.",
    "seed1": 2,
    "seed2": 8,
    "book_odds_home": 2.45,
    "book_odds_away": 1.52,
    "tournament": "Queen's Club",
    "surface": "grass",
    "category": "A500",
    "tour": "ATP"
  },
  {
    "time": "",
    "player1": "Sun L.",
    "player2": "Kalinina A.",
    "seed1": null,
    "seed2": 8,
    "book_odds_home": 2.44,
    "book_odds_away": 1.53,
    "tournament": "Berlin",
    "surface": "grass",
    "category": "W500",
    "tour": "WTA"
  },
  {
    "time": "",
    "player1": "Parry D.",
    "player2": "Seidel E.",
    "seed1": 5,
    "seed2": null,
    "book_odds_home": 1.57,
    "book_odds_away": 2.33,
    "tournament": "Berlin",
    "surface": "grass",
    "category": "W500",
    "tour": "WTA"
  },
  {
    "time": "",
    "player1": "Lamens S.",
    "player2": "Galfi D.",
    "seed1": null,
    "seed2": null,
    "book_odds_home": 2.49,
    "book_odds_away": 1.5,
    "tournament": "Berlin",
    "surface": "grass",
    "category": "W500",
    "tour": "WTA"
  },
  {
    "time": "",
    "player1": "Brockmann T.",
    "player2": "Parks A.",
    "seed1": null,
    "seed2": 11,
    "book_odds_home": 5.53,
    "book_odds_away": 1.13,
    "tournament": "Berlin",
    "surface": "grass",
    "category": "W500",
    "tour": "WTA"
  },
  {
    "time": "",
    "player1": "Siniakova K.",
    "player2": "Yuan Y.",
    "seed1": 2,
    "seed2": null,
    "book_odds_home": 1.32,
    "book_odds_away": 3.25,
    "tournament": "Berlin",
    "surface": "grass",
    "category": "W500",
    "tour": "WTA"
  },
  {
    "time": "",
    "player1": "Marcinko P.",
    "player2": "Ito A.",
    "seed1": 4,
    "seed2": null,
    "book_odds_home": 1.54,
    "book_odds_away": 2.39,
    "tournament": "Berlin",
    "surface": "grass",
    "category": "W500",
    "tour": "WTA"
  },
  {
    "time": "15:15",
    "player1": "Timofeeva M.",
    "player2": "Zarazua R.",
    "seed1": null,
    "seed2": 9,
    "book_odds_home": 1.61,
    "book_odds_away": 2.23,
    "tournament": "Berlin",
    "surface": "grass",
    "category": "W500",
    "tour": "WTA"
  },
  {
    "time": "",
    "player1": "Frech M.",
    "player2": "Zhang S.",
    "seed1": 3,
    "seed2": 7,
    "book_odds_home": 1.69,
    "book_odds_away": 2.09,
    "tournament": "Berlin",
    "surface": "grass",
    "category": "W500",
    "tour": "WTA"
  },
  {
    "time": "",
    "player1": "Masarova R.",
    "player2": "Pohankova M.",
    "seed1": null,
    "seed2": null,
    "book_odds_home": 1.64,
    "book_odds_away": 2.17,
    "tournament": "Berlin",
    "surface": "grass",
    "category": "W500",
    "tour": "WTA"
  }
]