[
  {
    "time": "",
    "player1": "Faria J.",
    "player2": "Grenier H.",
    "seed1": 2,
    "seed2": null,
    "book_odds_home": 1.2,
    "book_odds_away": 4.37,
    "tournament": "Wimbledon",
    "surface": "grass",
    "category": "GS",
    "tour": "ATP",
    "name1": "Jaime\u00a0Faria",
    "name2": "Hugo\u00a0Grenier",
    "r1": {
      "elo_rank": 98,
      "age": 22.8,
      "elo": 1709.1,
      "hElo": 1602.1,
      "cElo": 1674.2,
      "gElo": 1616.5,
      "atp_rank": 93,
      "surface_score": 2
    },
    "r2": {
      "elo_rank": 215,
      "age": 30.2,
      "elo": 1555.1,
      "hElo": 1526.7,
      "cElo": 1419.0,
      "gElo": 1461.6,
      "atp_rank": 223,
      "surface_score": 5
    },
    "c_elo1": 1674.2,
    "h_elo1": 1602.1,
    "c_elo2": 1419.0,
    "h_elo2": 1526.7,
    "ss1": 3,
    "ss2": 8,
    "prob1": 0.7092359349377366,
    "odds1": 1.41,
    "odds2": 3.44,
    "edge1": -0.1241,
    "edge2": 0.0619,
    "court_cpi": 37,
    "elo_found": true,
    "error": null,
    "status": "upcoming"
  },
  {
    "time": "",
    "player1": "Lajal M.",
    "player2": "Pavlovic L.",
    "seed1": null,
    "seed2": null,
    "book_odds_home": 1.32,
    "book_odds_away": 3.3,
    "tournament": "Wimbledon",
    "surface": "grass",
    "category": "GS",
    "tour": "ATP",
    "name1": "Mark\u00a0Lajal",
    "name2": "Luka\u00a0Pavlovic",
    "r1": {
      "elo_rank": 167,
      "age": 23.0,
      "elo": 1617.6,
      "hElo": 1570.6,
      "cElo": 1504.1,
      "gElo": 1595.3,
      "atp_rank": 166,
      "surface_score": 4
    },
    "r2": {
      "elo_rank": 333,
      "age": 26.1,
      "elo": 1441.4,
      "hElo": 1429.3,
      "cElo": 1399.9,
      "gElo": 1448.6,
      "atp_rank": 219,
      "surface_score": 3
    },
    "c_elo1": 1504.1,
    "h_elo1": 1570.6,
    "c_elo2": 1399.9,
    "h_elo2": 1429.3,
    "ss1": 7,
    "ss2": 6,
    "prob1": 0.699406461790348,
    "odds1": 1.43,
    "odds2": 3.33,
    "edge1": -0.0582,
    "edge2": -0.0024,
    "court_cpi": 37,
    "elo_found": true,
    "error": null,
    "status": "upcoming"
  },
  {
    "time": "",
    "player1": "Chidekh C.",
    "player2": "Dougaz A.",
    "seed1": null,
    "seed2": null,
    "book_odds_home": 1.36,
    "book_odds_away": 3.05,
    "tournament": "Wimbledon",
    "surface": "grass",
    "category": "GS",
    "tour": "ATP",
    "elo_found": false,
    "error": "N/A: Dougaz A.",
    "status": "upcoming"
  },
  {
    "time": "",
    "player1": "Matusevich A.",
    "player2": "Sakamoto R.",
    "seed1": null,
    "seed2": 27,
    "book_odds_home": 2.04,
    "book_odds_away": 1.74,
    "tournament": "Wimbledon",
    "surface": "grass",
    "category": "GS",
    "tour": "ATP",
    "elo_found": false,
    "error": "N/A: Matusevich A.",
    "status": "upcoming"
  },
  {
    "time": "",
    "player1": "Yunchaokete B.",
    "player2": "Dellien H.",
    "seed1": 3,
    "seed2": null,
    "book_odds_home": 1.05,
    "book_odds_away": 9.63,
    "tournament": "Wimbledon",
    "surface": "grass",
    "category": "GS",
    "tour": "ATP",
    "name1": "Bu\u00a0Yunchaokete",
    "name2": "Hugo\u00a0Dellien",
    "r1": {
      "elo_rank": 91,
      "age": 24.3,
      "elo": 1721.6,
      "hElo": 1650.4,
      "cElo": 1627.5,
      "gElo": 1644.4,
      "atp_rank": 107,
      "surface_score": 3
    },
    "r2": {
      "elo_rank": 165,
      "age": 32.9,
      "elo": 1620.1,
      "hElo": 1477.1,
      "cElo": 1607.2,
      "gElo": 1470.8,
      "atp_rank": 163,
      "surface_score": 1
    },
    "c_elo1": 1627.5,
    "h_elo1": 1650.4,
    "c_elo2": 1607.2,
    "h_elo2": 1477.1,
    "ss1": 6,
    "ss2": 2,
    "prob1": 0.7309252411617174,
    "odds1": 1.37,
    "odds2": 3.72,
    "edge1": -0.2215,
    "edge2": 0.1652,
    "court_cpi": 37,
    "elo_found": true,
    "error": null,
    "status": "upcoming"
  },
  {
    "time": "",
    "player1": "Gomez F.",
    "player2": "Tabur C.",
    "seed1": null,
    "seed2": null,
    "book_odds_home": 2.69,
    "book_odds_away": 1.44,
    "tournament": "Wimbledon",
    "surface": "grass",
    "category": "GS",
    "tour": "ATP",
    "name1": "Federico\u00a0Agustin\u00a0Gomez",
    "name2": "Clement\u00a0Tabur",
    "r1": {
      "elo_rank": 347,
      "age": 29.4,
      "elo": 1432.7,
      "hElo": 1396.5,
      "cElo": 1399.7,
      "gElo": 1424.3,
      "atp_rank": 214,
      "surface_score": 3
    },
    "r2": {
      "elo_rank": 175,
      "age": 26.3,
      "elo": 1605.4,
      "hElo": 1572.1,
      "cElo": 1549.7,
      "gElo": 1472.2,
      "atp_rank": 196,
      "surface_score": 3
    },
    "c_elo1": 1399.7,
    "h_elo1": 1396.5,
    "c_elo2": 1549.7,
    "h_elo2": 1572.1,
    "ss1": 5,
    "ss2": 6,
    "prob1": 0.43149981302179924,
    "odds1": 2.32,
    "odds2": 1.76,
    "edge1": 0.0598,
    "edge2": -0.1259,
    "court_cpi": 37,
    "elo_found": true,
    "error": null,
    "status": "upcoming"
  },
  {
    "time": "",
    "player1": "Wong C.",
    "player2": "Gojo B.",
    "seed1": 4,
    "seed2": null,
    "book_odds_home": 1.64,
    "book_odds_away": 2.21,
    "tournament": "Wimbledon",
    "surface": "grass",
    "category": "GS",
    "tour": "ATP",
    "name1": "Coleman\u00a0Wong",
    "name2": "Borna\u00a0Gojo",
    "r1": {
      "elo_rank": 157,
      "age": 22.0,
      "elo": 1626.2,
      "hElo": 1604.8,
      "cElo": 1440.1,
      "gElo": 1506.5,
      "atp_rank": 109,
      "surface_score": 5
    },
    "r2": {
      "elo_rank": 121,
      "age": 28.1,
      "elo": 1682.4,
      "hElo": 1661.9,
      "cElo": 1640.7,
      "gElo": 1467.9,
      "atp_rank": 184,
      "surface_score": 3
    },
    "c_elo1": 1440.1,
    "h_elo1": 1604.8,
    "c_elo2": 1640.7,
    "h_elo2": 1661.9,
    "ss1": 9,
    "ss2": 6,
    "prob1": 0.5553224347432761,
    "odds1": 1.8,
    "odds2": 2.25,
    "edge1": -0.0544,
    "edge2": -0.0078,
    "court_cpi": 37,
    "elo_found": true,
    "error": null,
    "status": "upcoming"
  },
  {
    "time": "",
    "player1": "Andrade A.",
    "player2": "Smith C.",
    "seed1": null,
    "seed2": null,
    "book_odds_home": 4.73,
    "book_odds_away": 1.17,
    "tournament": "Wimbledon",
    "surface": "grass",
    "category": "GS",
    "tour": "ATP",
    "name1": "Andres\u00a0Andrade",
    "name2": "Colton\u00a0Smith",
    "r1": {
      "elo_rank": 250,
      "age": 27.4,
      "elo": 1518.0,
      "hElo": 1433.3,
      "cElo": 1500.8,
      "gElo": 1459.0,
      "atp_rank": 239,
      "surface_score": 2
    },
    "r2": {
      "elo_rank": 192,
      "age": 23.2,
      "elo": 1580.7,
      "hElo": 1567.2,
      "cElo": 1460.4,
      "gElo": 1559.2,
      "atp_rank": 177,
      "surface_score": 5
    },
    "c_elo1": 1500.8,
    "h_elo1": 1433.3,
    "c_elo2": 1460.4,
    "h_elo2": 1567.2,
    "ss1": 3,
    "ss2": 8,
    "prob1": 0.3596698061460955,
    "odds1": 2.78,
    "odds2": 1.56,
    "edge1": 0.1483,
    "edge2": -0.2144,
    "court_cpi": 37,
    "elo_found": true,
    "error": null,
    "status": "upcoming"
  },
  {
    "time": "",
    "player1": "Djere L.",
    "player2": "Houkes M.",
    "seed1": null,
    "seed2": null,
    "book_odds_home": 1.24,
    "book_odds_away": 3.87,
    "tournament": "Wimbledon",
    "surface": "grass",
    "category": "GS",
    "tour": "ATP",
    "name1": "Laslo\u00a0Djere",
    "name2": "Max\u00a0Houkes",
    "r1": {
      "elo_rank": 108,
      "age": 31.0,
      "elo": 1695.1,
      "hElo": 1612.1,
      "cElo": 1707.0,
      "gElo": 1570.2,
      "atp_rank": 225,
      "surface_score": 2
    },
    "r2": {
      "elo_rank": 294,
      "age": 25.9,
      "elo": 1475.7,
      "hElo": 1312.5,
      "cElo": 1459.7,
      "gElo": 1391.4,
      "atp_rank": 231,
      "surface_score": 1
    },
    "c_elo1": 1707.0,
    "h_elo1": 1612.1,
    "c_elo2": 1459.7,
    "h_elo2": 1312.5,
    "ss1": 2,
    "ss2": 2,
    "prob1": 0.7367715406149334,
    "odds1": 1.36,
    "odds2": 3.8,
    "edge1": -0.0697,
    "edge2": 0.0048,
    "court_cpi": 37,
    "elo_found": true,
    "error": null,
    "status": "upcoming"
  },
  {
    "time": "",
    "player1": "Squire H.",
    "player2": "Zheng M.",
    "seed1": null,
    "seed2": 26,
    "book_odds_home": 2.74,
    "book_odds_away": 1.43,
    "tournament": "Wimbledon",
    "surface": "grass",
    "category": "GS",
    "tour": "ATP",
    "name1": "Henri\u00a0Squire",
    "name2": "Michael\u00a0Zheng",
    "r1": {
      "elo_rank": 238,
      "age": 25.6,
      "elo": 1533.9,
      "hElo": 1470.7,
      "cElo": 1516.2,
      "gElo": 1380.4,
      "atp_rank": 235,
      "surface_score": 2
    },
    "r2": {
      "elo_rank": 120,
      "age": 22.3,
      "elo": 1682.8,
      "hElo": 1665.3,
      "cElo": 1442.5,
      "gElo": 1522.0,
      "atp_rank": 146,
      "surface_score": 5
    },
    "c_elo1": 1516.2,
    "h_elo1": 1470.7,
    "c_elo2": 1442.5,
    "h_elo2": 1665.3,
    "ss1": 3,
    "ss2": 9,
    "prob1": 0.30680156643559325,
    "odds1": 3.26,
    "odds2": 1.44,
    "edge1": -0.0582,
    "edge2": -0.0061,
    "court_cpi": 37,
    "elo_found": true,
    "error": null,
    "status": "upcoming"
  },
  {
    "time": "",
    "player1": "Gaston H.",
    "player2": "Midon L.",
    "seed1": 5,
    "seed2": null,
    "book_odds_home": 1.22,
    "book_odds_away": 4.1,
    "tournament": "Wimbledon",
    "surface": "grass",
    "category": "GS",
    "tour": "ATP",
    "name1": "Hugo\u00a0Gaston",
    "name2": "Lautaro\u00a0Midon",
    "r1": {
      "elo_rank": 148,
      "age": 25.6,
      "elo": 1637.4,
      "hElo": 1635.7,
      "cElo": 1573.7,
      "gElo": 1542.9,
      "atp_rank": 117,
      "surface_score": 4
    },
    "r2": {
      "elo_rank": 234,
      "age": 22.1,
      "elo": 1538.0,
      "hElo": 1457.3,
      "cElo": 1520.9,
      "gElo": 1469.0,
      "atp_rank": 227,
      "surface_score": 2
    },
    "c_elo1": 1573.7,
    "h_elo1": 1635.7,
    "c_elo2": 1520.9,
    "h_elo2": 1457.3,
    "ss1": 7,
    "ss2": 3,
    "prob1": 0.6047753181100043,
    "odds1": 1.65,
    "odds2": 2.53,
    "edge1": -0.2149,
    "edge2": 0.1513,
    "court_cpi": 37,
    "elo_found": true,
    "error": null,
    "status": "upcoming"
  },
  {
    "time": "",
    "player1": "Cadenasso G.",
    "player2": "Cina F.",
    "seed1": null,
    "seed2": null,
    "book_odds_home": 3.16,
    "book_odds_away": 1.34,
    "tournament": "Wimbledon",
    "surface": "grass",
    "category": "GS",
    "tour": "ATP",
    "name1": "Gianluca\u00a0Cadenasso",
    "name2": "Federico\u00a0Cina",
    "r1": {
      "elo_rank": 243,
      "age": 21.6,
      "elo": 1527.9,
      "hElo": 1374.0,
      "cElo": 1504.4,
      "gElo": 1464.0,
      "atp_rank": null,
      "surface_score": 1
    },
    "r2": {
      "elo_rank": 188,
      "age": 19.1,
      "elo": 1582.8,
      "hElo": 1559.5,
      "cElo": 1539.6,
      "gElo": 1491.4,
      "atp_rank": 181,
      "surface_score": 3
    },
    "c_elo1": 1504.4,
    "h_elo1": 1374.0,
    "c_elo2": 1539.6,
    "h_elo2": 1559.5,
    "ss1": 2,
    "ss2": 6,
    "prob1": 0.4606497754982693,
    "odds1": 2.17,
    "odds2": 1.85,
    "edge1": 0.1442,
    "edge2": -0.2069,
    "court_cpi": 37,
    "elo_found": true,
    "error": null,
    "status": "upcoming"
  },
  {
    "time": "",
    "player1": "Safiullin R.",
    "player2": "McCabe J.",
    "seed1": 15,
    "seed2": null,
    "book_odds_home": 1.42,
    "book_odds_away": 2.76,
    "tournament": "Wimbledon",
    "surface": "grass",
    "category": "GS",
    "tour": "ATP",
    "name1": "Roman\u00a0Safiullin",
    "name2": "James\u00a0Mccabe",
    "r1": {
      "elo_rank": 86,
      "age": 28.8,
      "elo": 1734.9,
      "hElo": 1696.1,
      "cElo": 1734.9,
      "gElo": 1587.4,
      "atp_rank": 131,
      "surface_score": 3
    },
    "r2": {
      "elo_rank": 223,
      "age": 22.9,
      "elo": 1545.8,
      "hElo": 1488.3,
      "cElo": 1336.4,
      "gElo": 1543.7,
      "atp_rank": 205,
      "surface_score": 5
    },
    "c_elo1": 1734.9,
    "h_elo1": 1696.1,
    "c_elo2": 1336.4,
    "h_elo2": 1488.3,
    "ss1": 3,
    "ss2": 9,
    "prob1": 0.562559798181811,
    "odds1": 1.78,
    "odds2": 2.29,
    "edge1": -0.1417,
    "edge2": 0.0751,
    "court_cpi": 37,
    "elo_found": true,
    "error": null,
    "status": "upcoming"
  },
  {
    "time": "",
    "player1": "Glinka D.",
    "player2": "Coppejans K.",
    "seed1": null,
    "seed2": null,
    "book_odds_home": 1.82,
    "book_odds_away": 1.94,
    "tournament": "Wimbledon",
    "surface": "grass",
    "category": "GS",
    "tour": "ATP",
    "name1": "Daniil\u00a0Glinka",
    "name2": "Kimmer\u00a0Coppejans",
    "r1": {
      "elo_rank": 259,
      "age": 26.0,
      "elo": 1510.4,
      "hElo": 1507.5,
      "cElo": 1451.1,
      "gElo": 1474.7,
      "atp_rank": 170,
      "surface_score": 4
    },
    "r2": {
      "elo_rank": 209,
      "age": 32.3,
      "elo": 1561.7,
      "hElo": 1478.1,
      "cElo": 1535.3,
      "gElo": 1464.4,
      "atp_rank": 221,
      "surface_score": 2
    },
    "c_elo1": 1451.1,
    "h_elo1": 1507.5,
    "c_elo2": 1535.3,
    "h_elo2": 1478.1,
    "ss1": 7,
    "ss2": 3,
    "prob1": 0.5148185505851798,
    "odds1": 1.94,
    "odds2": 2.06,
    "edge1": -0.0346,
    "edge2": -0.0303,
    "court_cpi": 37,
    "elo_found": true,
    "error": null,
    "status": "upcoming"
  },
  {
    "time": "",
    "player1": "Piros Z.",
    "player2": "Ivanov I.",
    "seed1": null,
    "seed2": null,
    "book_odds_home": 1.41,
    "book_odds_away": 2.83,
    "tournament": "Wimbledon",
    "surface": "grass",
    "category": "GS",
    "tour": "ATP",
    "elo_found": false,
    "error": "N/A: Ivanov I.",
    "status": "upcoming"
  },
  {
    "time": "",
    "player1": "Napolitano S.",
    "player2": "Harris B.",
    "seed1": null,
    "seed2": 23,
    "book_odds_home": 3.79,
    "book_odds_away": 1.25,
    "tournament": "Wimbledon",
    "surface": "grass",
    "category": "GS",
    "tour": "ATP",
    "name1": "Stefano\u00a0Napolitano",
    "name2": "Billy\u00a0Harris",
    "r1": {
      "elo_rank": 230,
      "age": 31.1,
      "elo": 1542.9,
      "hElo": 1463.9,
      "cElo": 1541.5,
      "gElo": 1490.3,
      "atp_rank": 245,
      "surface_score": 2
    },
    "r2": {
      "elo_rank": 283,
      "age": 31.3,
      "elo": 1485.8,
      "hElo": 1461.5,
      "cElo": 1364.8,
      "gElo": 1492.9,
      "atp_rank": 142,
      "surface_score": 4
    },
    "c_elo1": 1541.5,
    "h_elo1": 1463.9,
    "c_elo2": 1364.8,
    "h_elo2": 1461.5,
    "ss1": 3,
    "ss2": 8,
    "prob1": 0.49625836906902093,
    "odds1": 2.02,
    "odds2": 1.99,
    "edge1": 0.2324,
    "edge2": -0.2963,
    "court_cpi": 37,
    "elo_found": true,
    "error": null,
    "status": "upcoming"
  },
  {
    "time": "",
    "player1": "Moreno De Alboran N.",
    "player2": "Mayot H.",
    "seed1": null,
    "seed2": null,
    "book_odds_home": 2.73,
    "book_odds_away": 1.44,
    "tournament": "Wimbledon",
    "surface": "grass",
    "category": "GS",
    "tour": "ATP",
    "elo_found": false,
    "error": "N/A: Moreno De Alboran N.",
    "status": "upcoming"
  },
  {
    "time": "",
    "player1": "Sanchez Izquierdo N.",
    "player2": "Kwon S.",
    "seed1": null,
    "seed2": null,
    "book_odds_home": 6.47,
    "book_odds_away": 1.11,
    "tournament": "Wimbledon",
    "surface": "grass",
    "category": "GS",
    "tour": "ATP",
    "name1": "Nikolas\u00a0Sanchez\u00a0Izquierdo",
    "name2": "Soon\u00a0Woo\u00a0Kwon",
    "r1": {
      "elo_rank": 197,
      "age": 27.2,
      "elo": 1572.1,
      "hElo": 1337.0,
      "cElo": 1544.5,
      "gElo": 1486.1,
      "atp_rank": 216,
      "surface_score": 1
    },
    "r2": {
      "elo_rank": 70,
      "age": 28.4,
      "elo": 1758.6,
      "hElo": 1722.7,
      "cElo": 1632.4,
      "gElo": 1603.3,
      "atp_rank": 208,
      "surface_score": 4
    },
    "c_elo1": 1544.5,
    "h_elo1": 1337.0,
    "c_elo2": 1632.4,
    "h_elo2": 1722.7,
    "ss1": 1,
    "ss2": 8,
    "prob1": 0.3374547495344342,
    "odds1": 2.96,
    "odds2": 1.51,
    "edge1": 0.1829,
    "edge2": -0.2384,
    "court_cpi": 37,
    "elo_found": true,
    "error": null,
    "status": "upcoming"
  },
  {
    "time": "",
    "player1": "Brancaccio R.",
    "player2": "Gea A.",
    "seed1": null,
    "seed2": 18,
    "book_odds_home": 3.78,
    "book_odds_away": 1.26,
    "tournament": "Wimbledon",
    "surface": "grass",
    "category": "GS",
    "tour": "ATP",
    "name1": "Raul\u00a0Brancaccio",
    "name2": "Arthur\u00a0Gea",
    "r1": {
      "elo_rank": 273,
      "age": 29.0,
      "elo": 1498.3,
      "hElo": 1424.8,
      "cElo": 1472.3,
      "gElo": 1418.7,
      "atp_rank": 236,
      "surface_score": 2
    },
    "r2": {
      "elo_rank": 169,
      "age": 21.3,
      "elo": 1613.9,
      "hElo": 1618.2,
      "cElo": 1529.7,
      "gElo": 1507.0,
      "atp_rank": 135,
      "surface_score": 4
    },
    "c_elo1": 1472.3,
    "h_elo1": 1424.8,
    "c_elo2": 1529.7,
    "h_elo2": 1618.2,
    "ss1": 3,
    "ss2": 8,
    "prob1": 0.3755931476907139,
    "odds1": 2.66,
    "odds2": 1.6,
    "edge1": 0.111,
    "edge2": -0.1692,
    "court_cpi": 37,
    "elo_found": true,
    "error": null,
    "status": "upcoming"
  },
  {
    "time": "",
    "player1": "Giustino L.",
    "player2": "Onclin G.",
    "seed1": null,
    "seed2": null,
    "book_odds_home": 5.92,
    "book_odds_away": 1.12,
    "tournament": "Wimbledon",
    "surface": "grass",
    "category": "GS",
    "tour": "ATP",
    "name1": "Lorenzo\u00a0Giustino",
    "name2": "Gauthier\u00a0Onclin",
    "r1": {
      "elo_rank": 341,
      "age": 34.7,
      "elo": 1435.2,
      "hElo": 1433.2,
      "cElo": 1369.6,
      "gElo": 1323.4,
      "atp_rank": 210,
      "surface_score": 4
    },
    "r2": {
      "elo_rank": 195,
      "age": 25.2,
      "elo": 1579.0,
      "hElo": 1558.0,
      "cElo": 1502.5,
      "gElo": 1538.5,
      "atp_rank": 186,
      "surface_score": 4
    },
    "c_elo1": 1369.6,
    "h_elo1": 1433.2,
    "c_elo2": 1502.5,
    "h_elo2": 1558.0,
    "ss1": 7,
    "ss2": 7,
    "prob1": 0.22474682033454724,
    "odds1": 4.45,
    "odds2": 1.29,
    "edge1": 0.0558,
    "edge2": -0.1176,
    "court_cpi": 37,
    "elo_found": true,
    "error": null,
    "status": "upcoming"
  },
  {
    "time": "",
    "player1": "Sachko V.",
    "player2": "Mochizuki S.",
    "seed1": null,
    "seed2": 21,
    "book_odds_home": 3.14,
    "book_odds_away": 1.34,
    "tournament": "Wimbledon",
    "surface": "grass",
    "category": "GS",
    "tour": "ATP",
    "name1": "Vitaliy\u00a0Sachko",
    "name2": "Shintaro\u00a0Mochizuki",
    "r1": {
      "elo_rank": 187,
      "age": 28.9,
      "elo": 1583.5,
      "hElo": 1474.9,
      "cElo": 1552.7,
      "gElo": 1438.5,
      "atp_rank": 199,
      "surface_score": 2
    },
    "r2": {
      "elo_rank": 316,
      "age": 23.0,
      "elo": 1455.9,
      "hElo": 1415.6,
      "cElo": 1439.4,
      "gElo": 1511.2,
      "atp_rank": 138,
      "surface_score": 3
    },
    "c_elo1": 1552.7,
    "h_elo1": 1474.9,
    "c_elo2": 1439.4,
    "h_elo2": 1415.6,
    "ss1": 3,
    "ss2": 4,
    "prob1": 0.396876977588092,
    "odds1": 2.52,
    "odds2": 1.66,
    "edge1": 0.0784,
    "edge2": -0.1431,
    "court_cpi": 37,
    "elo_found": true,
    "error": null,
    "status": "upcoming"
  },
  {
    "time": "",
    "player1": "Smith K.",
    "player2": "Ficovich J.",
    "seed1": null,
    "seed2": null,
    "book_odds_home": 1.53,
    "book_odds_away": 2.44,
    "tournament": "Wimbledon",
    "surface": "grass",
    "category": "GS",
    "tour": "ATP",
    "name1": "Keegan\u00a0Smith",
    "name2": "Juan\u00a0Pablo\u00a0Ficovich",
    "r1": {
      "elo_rank": 360,
      "age": 27.9,
      "elo": 1421.0,
      "hElo": 1394.6,
      "cElo": 1253.6,
      "gElo": 1410.5,
      "atp_rank": 246,
      "surface_score": 5
    },
    "r2": {
      "elo_rank": 348,
      "age": 29.3,
      "elo": 1431.0,
      "hElo": 1426.6,
      "cElo": 1395.2,
      "gElo": 1428.3,
      "atp_rank": 198,
      "surface_score": 3
    },
    "c_elo1": 1253.6,
    "h_elo1": 1394.6,
    "c_elo2": 1395.2,
    "h_elo2": 1426.6,
    "ss1": 8,
    "ss2": 7,
    "prob1": 0.4744061296054041,
    "odds1": 2.11,
    "odds2": 1.9,
    "edge1": -0.1792,
    "edge2": 0.1158,
    "court_cpi": 37,
    "elo_found": true,
    "error": null,
    "status": "upcoming"
  },
  {
    "time": "",
    "player1": "Butvilas E.",
    "player2": "Echargui M.",
    "seed1": null,
    "seed2": 29,
    "book_odds_home": 1.37,
    "book_odds_away": 2.99,
    "tournament": "Wimbledon",
    "surface": "grass",
    "category": "GS",
    "tour": "ATP",
    "name1": "Edas\u00a0Butvilas",
    "name2": "Moez\u00a0Echargui",
    "r1": {
      "elo_rank": 226,
      "age": 21.8,
      "elo": 1544.4,
      "hElo": 1499.1,
      "cElo": 1501.1,
      "gElo": 1456.1,
      "atp_rank": 229,
      "surface_score": 3
    },
    "r2": {
      "elo_rank": 344,
      "age": 33.3,
      "elo": 1434.5,
      "hElo": 1417.1,
      "cElo": 1360.6,
      "gElo": 1417.3,
      "atp_rank": 150,
      "surface_score": 4
    },
    "c_elo1": 1501.1,
    "h_elo1": 1499.1,
    "c_elo2": 1360.6,
    "h_elo2": 1417.1,
    "ss1": 5,
    "ss2": 7,
    "prob1": 0.5556067161284776,
    "odds1": 1.8,
    "odds2": 2.25,
    "edge1": -0.1743,
    "edge2": 0.1099,
    "court_cpi": 37,
    "elo_found": true,
    "error": null,
    "status": "upcoming"
  },
  {
    "time": "",
    "player1": "Basilashvili N.",
    "player2": "Ymer E.",
    "seed1": 6,
    "seed2": null,
    "book_odds_home": 1.54,
    "book_odds_away": 2.41,
    "tournament": "Wimbledon",
    "surface": "grass",
    "category": "GS",
    "tour": "ATP",
    "name1": "Nikoloz\u00a0Basilashvili",
    "name2": "Elias\u00a0Ymer",
    "r1": {
      "elo_rank": 124,
      "age": 34.2,
      "elo": 1677.7,
      "hElo": 1611.4,
      "cElo": 1648.4,
      "gElo": 1609.6,
      "atp_rank": 118,
      "surface_score": 3
    },
    "r2": {
      "elo_rank": 202,
      "age": 30.1,
      "elo": 1568.3,
      "hElo": 1537.4,
      "cElo": 1509.1,
      "gElo": 1533.2,
      "atp_rank": 182,
      "surface_score": 3
    },
    "c_elo1": 1648.4,
    "h_elo1": 1611.4,
    "c_elo2": 1509.1,
    "h_elo2": 1537.4,
    "ss1": 3,
    "ss2": 6,
    "prob1": 0.6082098850611125,
    "odds1": 1.64,
    "odds2": 2.55,
    "edge1": -0.0411,
    "edge2": -0.0231,
    "court_cpi": 37,
    "elo_found": true,
    "error": null,
    "status": "upcoming"
  },
  {
    "time": "",
    "player1": "Skatov T.",
    "player2": "Barrena A.",
    "seed1": null,
    "seed2": null,
    "book_odds_home": 1.24,
    "book_odds_away": 3.86,
    "tournament": "Wimbledon",
    "surface": "grass",
    "category": "GS",
    "tour": "ATP",
    "name1": "Timofey\u00a0Skatov",
    "name2": "Alex\u00a0Barrena",
    "r1": {
      "elo_rank": 216,
      "age": 25.3,
      "elo": 1554.1,
      "hElo": 1484.4,
      "cElo": 1541.5,
      "gElo": 1489.1,
      "atp_rank": 176,
      "surface_score": 2
    },
    "r2": {
      "elo_rank": 401,
      "age": 23.6,
      "elo": 1385.1,
      "hElo": 1260.7,
      "cElo": 1361.7,
      "gElo": 1392.5,
      "atp_rank": 207,
      "surface_score": 1
    },
    "c_elo1": 1541.5,
    "h_elo1": 1484.4,
    "c_elo2": 1361.7,
    "h_elo2": 1260.7,
    "ss1": 3,
    "ss2": 2,
    "prob1": 0.6355437233808091,
    "odds1": 1.57,
    "odds2": 2.74,
    "edge1": -0.1709,
    "edge2": 0.1054,
    "court_cpi": 37,
    "elo_found": true,
    "error": null,
    "status": "upcoming"
  },
  {
    "time": "",
    "player1": "Guerrieri A.",
    "player2": "Goffin D.",
    "seed1": null,
    "seed2": null,
    "book_odds_home": 2.3,
    "book_odds_away": 1.59,
    "tournament": "Wimbledon",
    "surface": "grass",
    "category": "GS",
    "tour": "ATP",
    "name1": "Andrea\u00a0Guerrieri",
    "name2": "David\u00a0Goffin",
    "r1": {
      "elo_rank": 224,
      "age": 27.5,
      "elo": 1545.4,
      "hElo": 1393.7,
      "cElo": 1509.9,
      "gElo": 1472.7,
      "atp_rank": 230,
      "surface_score": 1
    },
    "r2": {
      "elo_rank": 130,
      "age": 35.3,
      "elo": 1666.6,
      "hElo": 1626.4,
      "cElo": 1643.1,
      "gElo": 1650.1,
      "atp_rank": 242,
      "surface_score": 3
    },
    "c_elo1": 1509.9,
    "h_elo1": 1393.7,
    "c_elo2": 1643.1,
    "h_elo2": 1626.4,
    "ss1": 2,
    "ss2": 4,
    "prob1": 0.26479440456357267,
    "odds1": 3.78,
    "odds2": 1.36,
    "edge1": -0.17,
    "edge2": 0.1063,
    "court_cpi": 37,
    "elo_found": true,
    "error": null,
    "status": "upcoming"
  },
  {
    "time": "",
    "player1": "Boscardin Dias P.",
    "player2": "Jacquet K.",
    "seed1": null,
    "seed2": 25,
    "book_odds_home": 6.76,
    "book_odds_away": 1.1,
    "tournament": "Wimbledon",
    "surface": "grass",
    "category": "GS",
    "tour": "ATP",
    "name1": "Pedro\u00a0Boscardin\u00a0Dias",
    "name2": "Kyrian\u00a0Jacquet",
    "r1": {
      "elo_rank": 290,
      "age": 23.3,
      "elo": 1479.3,
      "hElo": 1272.0,
      "cElo": 1463.1,
      "gElo": 1439.7,
      "atp_rank": 241,
      "surface_score": 1
    },
    "r2": {
      "elo_rank": 140,
      "age": 25.0,
      "elo": 1647.2,
      "hElo": 1644.0,
      "cElo": 1540.9,
      "gElo": 1546.4,
      "atp_rank": 145,
      "surface_score": 5
    },
    "c_elo1": 1463.1,
    "h_elo1": 1272.0,
    "c_elo2": 1540.9,
    "h_elo2": 1644.0,
    "ss1": 1,
    "ss2": 8,
    "prob1": 0.35109839720257796,
    "odds1": 2.85,
    "odds2": 1.54,
    "edge1": 0.2032,
    "edge2": -0.2602,
    "court_cpi": 37,
    "elo_found": true,
    "error": null,
    "status": "upcoming"
  },
  {
    "time": "",
    "player1": "Prado Angelo J.",
    "player2": "Evans D.",
    "seed1": null,
    "seed2": null,
    "book_odds_home": 3.47,
    "book_odds_away": 1.29,
    "tournament": "Wimbledon",
    "surface": "grass",
    "category": "GS",
    "tour": "ATP",
    "elo_found": false,
    "error": "N/A: Prado Angelo J.",
    "status": "upcoming"
  },
  {
    "time": "",
    "player1": "Monday J.",
    "player2": "Schoolkate T.",
    "seed1": null,
    "seed2": 28,
    "book_odds_home": 2.52,
    "book_odds_away": 1.5,
    "tournament": "Wimbledon",
    "surface": "grass",
    "category": "GS",
    "tour": "ATP",
    "name1": "Johannus\u00a0Monday",
    "name2": "Tristan\u00a0Schoolkate",
    "r1": {
      "elo_rank": 328,
      "age": 24.3,
      "elo": 1449.5,
      "hElo": 1421.1,
      "cElo": 1334.8,
      "gElo": 1374.9,
      "atp_rank": 294,
      "surface_score": 4
    },
    "r2": {
      "elo_rank": 218,
      "age": 25.2,
      "elo": 1550.4,
      "hElo": 1515.2,
      "cElo": 1443.8,
      "gElo": 1533.9,
      "atp_rank": 149,
      "surface_score": 4
    },
    "c_elo1": 1334.8,
    "h_elo1": 1421.1,
    "c_elo2": 1443.8,
    "h_elo2": 1515.2,
    "ss1": 8,
    "ss2": 7,
    "prob1": 0.2859210974146497,
    "odds1": 3.5,
    "odds2": 1.4,
    "edge1": -0.1109,
    "edge2": 0.0474,
    "court_cpi": 37,
    "elo_found": true,
    "error": null,
    "status": "upcoming"
  },
  {
    "time": "",
    "player1": "Tarvet O.",
    "player2": "Bolt A.",
    "seed1": null,
    "seed2": null,
    "book_odds_home": 2.01,
    "book_odds_away": 1.76,
    "tournament": "Wimbledon",
    "surface": "grass",
    "category": "GS",
    "tour": "ATP",
    "name1": "Oliver\u00a0Tarvet",
    "name2": "Alex\u00a0Bolt",
    "r1": {
      "elo_rank": 263,
      "age": 22.5,
      "elo": 1503.6,
      "hElo": 1467.2,
      "cElo": 1501.8,
      "gElo": 1543.7,
      "atp_rank": 344,
      "surface_score": 3
    },
    "r2": {
      "elo_rank": 176,
      "age": 33.3,
      "elo": 1601.4,
      "hElo": 1547.4,
      "cElo": 1427.6,
      "gElo": 1579.7,
      "atp_rank": 155,
      "surface_score": 5
    },
    "c_elo1": 1501.8,
    "h_elo1": 1467.2,
    "c_elo2": 1427.6,
    "h_elo2": 1547.4,
    "ss1": 3,
    "ss2": 8,
    "prob1": 0.4483764526890395,
    "odds1": 2.23,
    "odds2": 1.81,
    "edge1": -0.0491,
    "edge2": -0.0166,
    "court_cpi": 37,
    "elo_found": true,
    "error": null,
    "status": "upcoming"
  },
  {
    "time": "",
    "player1": "Hsu Y.",
    "player2": "Sakellaridis S.",
    "seed1": null,
    "seed2": 31,
    "book_odds_home": 2.22,
    "book_odds_away": 1.63,
    "tournament": "Wimbledon",
    "surface": "grass",
    "category": "GS",
    "tour": "ATP",
    "name1": "Yu\u00a0Hsiou\u00a0Hsu",
    "name2": "Stefanos\u00a0Sakellaridis",
    "r1": {
      "elo_rank": 267,
      "age": 27.1,
      "elo": 1502.2,
      "hElo": 1475.3,
      "cElo": 1423.6,
      "gElo": 1342.3,
      "atp_rank": 213,
      "surface_score": 4
    },
    "r2": {
      "elo_rank": 150,
      "age": 21.7,
      "elo": 1634.3,
      "hElo": 1567.9,
      "cElo": 1627.3,
      "gElo": 1542.3,
      "atp_rank": 153,
      "surface_score": 2
    },
    "c_elo1": 1423.6,
    "h_elo1": 1475.3,
    "c_elo2": 1627.3,
    "h_elo2": 1567.9,
    "ss1": 7,
    "ss2": 3,
    "prob1": 0.2402530733520421,
    "odds1": 4.16,
    "odds2": 1.32,
    "edge1": -0.2102,
    "edge2": 0.1462,
    "court_cpi": 37,
    "elo_found": true,
    "error": null,
    "status": "upcoming"
  },
  {
    "time": "",
    "player1": "Comesana F.",
    "player2": "Moro Canas A.",
    "seed1": 1,
    "seed2": null,
    "book_odds_home": 1.43,
    "book_odds_away": 2.77,
    "tournament": "Wimbledon",
    "surface": "grass",
    "category": "GS",
    "tour": "ATP",
    "name1": "Francisco\u00a0Comesana",
    "name2": "Alejandro\u00a0Moro\u00a0Canas",
    "r1": {
      "elo_rank": 109,
      "age": 25.6,
      "elo": 1694.8,
      "hElo": 1641.8,
      "cElo": 1656.0,
      "gElo": 1560.3,
      "atp_rank": 88,
      "surface_score": 3
    },
    "r2": {
      "elo_rank": 220,
      "age": 25.5,
      "elo": 1546.9,
      "hElo": 1528.9,
      "cElo": 1504.0,
      "gElo": 1496.8,
      "atp_rank": 233,
      "surface_score": 3
    },
    "c_elo1": 1656.0,
    "h_elo1": 1641.8,
    "c_elo2": 1504.0,
    "h_elo2": 1528.9,
    "ss1": 4,
    "ss2": 6,
    "prob1": 0.5903797307925488,
    "odds1": 1.69,
    "odds2": 2.44,
    "edge1": -0.1089,
    "edge2": 0.0486,
    "court_cpi": 37,
    "elo_found": true,
    "error": null,
    "status": "upcoming"
  },
  {
    "time": "",
    "player1": "Llamas Ruiz P.",
    "player2": "Added D.",
    "seed1": 7,
    "seed2": null,
    "book_odds_home": 1.22,
    "book_odds_away": 4.08,
    "tournament": "Wimbledon",
    "surface": "grass",
    "category": "GS",
    "tour": "ATP",
    "name1": "Pablo\u00a0Llamas\u00a0Ruiz",
    "name2": "Dan\u00a0Added",
    "r1": {
      "elo_rank": 87,
      "age": 23.6,
      "elo": 1733.6,
      "hElo": 1618.8,
      "cElo": 1709.6,
      "gElo": 1558.0,
      "atp_rank": 120,
      "surface_score": 2
    },
    "r2": {
      "elo_rank": 355,
      "age": 27.0,
      "elo": 1426.0,
      "hElo": 1405.9,
      "cElo": 1291.5,
      "gElo": 1413.0,
      "atp_rank": 240,
      "surface_score": 5
    },
    "c_elo1": 1709.6,
    "h_elo1": 1618.8,
    "c_elo2": 1291.5,
    "h_elo2": 1405.9,
    "ss1": 2,
    "ss2": 8,
    "prob1": 0.6973450785898532,
    "odds1": 1.43,
    "odds2": 3.3,
    "edge1": -0.1223,
    "edge2": 0.0576,
    "court_cpi": 37,
    "elo_found": true,
    "error": null,
    "status": "upcoming"
  },
  {
    "time": "",
    "player1": "Bailly G.",
    "player2": "Martin Tiffon P.",
    "seed1": null,
    "seed2": null,
    "book_odds_home": 1.83,
    "book_odds_away": 1.92,
    "tournament": "Wimbledon",
    "surface": "grass",
    "category": "GS",
    "tour": "ATP",
    "name1": "Gilles\u00a0Arnaud\u00a0Bailly",
    "name2": "Pol\u00a0Martin\u00a0Tiffon",
    "r1": {
      "elo_rank": 256,
      "age": 20.6,
      "elo": 1512.9,
      "hElo": 1475.5,
      "cElo": 1480.1,
      "gElo": 1506.5,
      "atp_rank": 215,
      "surface_score": 3
    },
    "r2": {
      "elo_rank": 210,
      "age": 26.8,
      "elo": 1560.9,
      "hElo": 1544.6,
      "cElo": 1506.2,
      "gElo": 1447.7,
      "atp_rank": 220,
      "surface_score": 3
    },
    "c_elo1": 1480.1,
    "h_elo1": 1475.5,
    "c_elo2": 1506.2,
    "h_elo2": 1544.6,
    "ss1": 5,
    "ss2": 7,
    "prob1": 0.5838212516844689,
    "odds1": 1.71,
    "odds2": 2.4,
    "edge1": 0.0374,
    "edge2": -0.1047,
    "court_cpi": 37,
    "elo_found": true,
    "error": null,
    "status": "upcoming"
  },
  {
    "time": "",
    "player1": "Boyer T.",
    "player2": "Olivieri G.",
    "seed1": null,
    "seed2": null,
    "book_odds_home": 1.16,
    "book_odds_away": 5.01,
    "tournament": "Wimbledon",
    "surface": "grass",
    "category": "GS",
    "tour": "ATP",
    "name1": "Tristan\u00a0Boyer",
    "name2": "Genaro\u00a0Alberto\u00a0Olivieri",
    "r1": {
      "elo_rank": 189,
      "age": 25.1,
      "elo": 1582.5,
      "hElo": 1535.8,
      "cElo": 1555.2,
      "gElo": 1463.6,
      "atp_rank": 191,
      "surface_score": 3
    },
    "r2": {
      "elo_rank": 255,
      "age": 27.8,
      "elo": 1513.4,
      "hElo": 1365.9,
      "cElo": 1491.7,
      "gElo": 1381.6,
      "atp_rank": 202,
      "surface_score": 1
    },
    "c_elo1": 1555.2,
    "h_elo1": 1535.8,
    "c_elo2": 1491.7,
    "h_elo2": 1365.9,
    "ss1": 4,
    "ss2": 2,
    "prob1": 0.615864104253756,
    "odds1": 1.62,
    "odds2": 2.6,
    "edge1": -0.2462,
    "edge2": 0.1845,
    "court_cpi": 37,
    "elo_found": true,
    "error": null,
    "status": "upcoming"
  },
  {
    "time": "",
    "player1": "Clarke J.",
    "player2": "Pellegrino A.",
    "seed1": null,
    "seed2": 17,
    "book_odds_home": 1.34,
    "book_odds_away": 3.13,
    "tournament": "Wimbledon",
    "surface": "grass",
    "category": "GS",
    "tour": "ATP",
    "name1": "Jay\u00a0Clarke",
    "name2": "Andrea\u00a0Pellegrino",
    "r1": {
      "elo_rank": 327,
      "age": 27.8,
      "elo": 1449.6,
      "hElo": 1416.4,
      "cElo": 1418.4,
      "gElo": 1346.5,
      "atp_rank": 250,
      "surface_score": 3
    },
    "r2": {
      "elo_rank": 141,
      "age": 29.1,
      "elo": 1645.7,
      "hElo": 1407.8,
      "cElo": 1628.5,
      "gElo": 1444.7,
      "atp_rank": 133,
      "surface_score": 1
    },
    "c_elo1": 1418.4,
    "h_elo1": 1416.4,
    "c_elo2": 1628.5,
    "h_elo2": 1407.8,
    "ss1": 5,
    "ss2": 1,
    "prob1": 0.36232557986155806,
    "odds1": 2.76,
    "odds2": 1.57,
    "edge1": -0.3839,
    "edge2": 0.3182,
    "court_cpi": 37,
    "elo_found": true,
    "error": null,
    "status": "upcoming"
  },
  {
    "time": "",
    "player1": "Budkov Kjaer N.",
    "player2": "Reis Da Silva J.",
    "seed1": 8,
    "seed2": null,
    "book_odds_home": 1.14,
    "book_odds_away": 5.43,
    "tournament": "Wimbledon",
    "surface": "grass",
    "category": "GS",
    "tour": "ATP",
    "elo_found": false,
    "error": "N/A: Reis Da Silva J.",
    "status": "upcoming"
  },
  {
    "time": "",
    "player1": "Dodig M.",
    "player2": "Silva F.",
    "seed1": null,
    "seed2": null,
    "book_odds_home": 2.12,
    "book_odds_away": 1.68,
    "tournament": "Wimbledon",
    "surface": "grass",
    "category": "GS",
    "tour": "ATP",
    "name1": "Matej\u00a0Dodig",
    "name2": "Frederico\u00a0Ferreira\u00a0Silva",
    "r1": {
      "elo_rank": 317,
      "age": 20.8,
      "elo": 1455.8,
      "hElo": 1404.1,
      "cElo": 1429.1,
      "gElo": 1427.9,
      "atp_rank": 212,
      "surface_score": 3
    },
    "r2": {
      "elo_rank": 289,
      "age": 31.1,
      "elo": 1482.9,
      "hElo": 1485.6,
      "cElo": 1416.2,
      "gElo": 1463.7,
      "atp_rank": 232,
      "surface_score": 4
    },
    "c_elo1": 1429.1,
    "h_elo1": 1404.1,
    "c_elo2": 1416.2,
    "h_elo2": 1485.6,
    "ss1": 4,
    "ss2": 7,
    "prob1": 0.4486612245354266,
    "odds1": 2.23,
    "odds2": 1.81,
    "edge1": -0.023,
    "edge2": -0.0439,
    "court_cpi": 37,
    "elo_found": true,
    "error": null,
    "status": "upcoming"
  },
  {
    "time": "",
    "player1": "Noguchi R.",
    "player2": "Nardi L.",
    "seed1": null,
    "seed2": null,
    "book_odds_home": 2.53,
    "book_odds_away": 1.49,
    "tournament": "Wimbledon",
    "surface": "grass",
    "category": "GS",
    "tour": "ATP",
    "name1": "Rio\u00a0Noguchi",
    "name2": "Luca\u00a0Nardi",
    "r1": {
      "elo_rank": 212,
      "age": 27.3,
      "elo": 1559.6,
      "hElo": 1526.4,
      "cElo": 1327.4,
      "gElo": 1434.7,
      "atp_rank": 218,
      "surface_score": 5
    },
    "r2": {
      "elo_rank": 179,
      "age": 22.8,
      "elo": 1600.5,
      "hElo": 1579.6,
      "cElo": 1543.6,
      "gElo": 1436.4,
      "atp_rank": 173,
      "surface_score": 3
    },
    "c_elo1": 1327.4,
    "h_elo1": 1526.4,
    "c_elo2": 1543.6,
    "h_elo2": 1579.6,
    "ss1": 9,
    "ss2": 7,
    "prob1": 0.49755352286267845,
    "odds1": 2.01,
    "odds2": 1.99,
    "edge1": 0.1023,
    "edge2": -0.1687,
    "court_cpi": 37,
    "elo_found": true,
    "error": null,
    "status": "upcoming"
  },
  {
    "time": "",
    "player1": "Virtanen O.",
    "player2": "Martinez P.",
    "seed1": null,
    "seed2": 19,
    "book_odds_home": 1.16,
    "book_odds_away": 5.0,
    "tournament": "Wimbledon",
    "surface": "grass",
    "category": "GS",
    "tour": "ATP",
    "name1": "Otto\u00a0Virtanen",
    "name2": "Pedro\u00a0Martinez",
    "r1": {
      "elo_rank": 110,
      "age": 24.9,
      "elo": 1694.4,
      "hElo": 1668.5,
      "cElo": 1536.9,
      "gElo": 1671.7,
      "atp_rank": 160,
      "surface_score": 5
    },
    "r2": {
      "elo_rank": 194,
      "age": 29.1,
      "elo": 1579.1,
      "hElo": 1551.7,
      "cElo": 1555.8,
      "gElo": 1451.0,
      "atp_rank": 136,
      "surface_score": 3
    },
    "c_elo1": 1536.9,
    "h_elo1": 1668.5,
    "c_elo2": 1555.8,
    "h_elo2": 1551.7,
    "ss1": 8,
    "ss2": 5,
    "prob1": 0.7808199975304106,
    "odds1": 1.28,
    "odds2": 4.56,
    "edge1": -0.0812,
    "edge2": 0.0192,
    "court_cpi": 37,
    "elo_found": true,
    "error": null,
    "status": "upcoming"
  },
  {
    "time": "",
    "player1": "Sweeny D.",
    "player2": "Roncadelli F.",
    "seed1": 11,
    "seed2": null,
    "book_odds_home": 1.06,
    "book_odds_away": 8.81,
    "tournament": "Wimbledon",
    "surface": "grass",
    "category": "GS",
    "tour": "ATP",
    "name1": "Dane\u00a0Sweeny",
    "name2": "Franco\u00a0Roncadelli",
    "r1": {
      "elo_rank": 279,
      "age": 25.2,
      "elo": 1488.6,
      "hElo": 1457.8,
      "cElo": 1309.5,
      "gElo": 1388.1,
      "atp_rank": 126,
      "surface_score": 5
    },
    "r2": {
      "elo_rank": 260,
      "age": 26.2,
      "elo": 1506.0,
      "hElo": 1381.9,
      "cElo": 1489.7,
      "gElo": 1453.0,
      "atp_rank": 226,
      "surface_score": 1
    },
    "c_elo1": 1309.5,
    "h_elo1": 1457.8,
    "c_elo2": 1489.7,
    "h_elo2": 1381.9,
    "ss1": 8,
    "ss2": 2,
    "prob1": 0.4076727666008392,
    "odds1": 2.45,
    "odds2": 1.69,
    "edge1": -0.5357,
    "edge2": 0.4788,
    "court_cpi": 37,
    "elo_found": true,
    "error": null,
    "status": "upcoming"
  },
  {
    "time": "",
    "player1": "Blanch D.",
    "player2": "Blanchet U.",
    "seed1": null,
    "seed2": null,
    "book_odds_home": 1.38,
    "book_odds_away": 2.96,
    "tournament": "Wimbledon",
    "surface": "grass",
    "category": "GS",
    "tour": "ATP",
    "name1": "Darwin\u00a0Blanch",
    "name2": "Ugo\u00a0Blanchet",
    "r1": {
      "elo_rank": 201,
      "age": 18.5,
      "elo": 1568.7,
      "hElo": 1491.8,
      "cElo": 1502.1,
      "gElo": 1484.3,
      "atp_rank": 211,
      "surface_score": 3
    },
    "r2": {
      "elo_rank": 253,
      "age": 27.3,
      "elo": 1515.5,
      "hElo": 1543.2,
      "cElo": 1433.4,
      "gElo": 1401.5,
      "atp_rank": 171,
      "surface_score": 5
    },
    "c_elo1": 1502.1,
    "h_elo1": 1491.8,
    "c_elo2": 1433.4,
    "h_elo2": 1543.2,
    "ss1": 4,
    "ss2": 8,
    "prob1": 0.6169529918097391,
    "odds1": 1.62,
    "odds2": 2.61,
    "edge1": -0.1077,
    "edge2": 0.0452,
    "court_cpi": 37,
    "elo_found": true,
    "error": null,
    "status": "upcoming"
  },
  {
    "time": "",
    "player1": "Diaz Acosta F.",
    "player2": "Galarneau A.",
    "seed1": 12,
    "seed2": null,
    "book_odds_home": 3.36,
    "book_odds_away": 1.31,
    "tournament": "Wimbledon",
    "surface": "grass",
    "category": "GS",
    "tour": "ATP",
    "name1": "Facundo\u00a0Diaz\u00a0Acosta",
    "name2": "Alexis\u00a0Galarneau",
    "r1": {
      "elo_rank": 151,
      "age": 25.4,
      "elo": 1634.2,
      "hElo": 1509.9,
      "cElo": 1629.7,
      "gElo": 1453.1,
      "atp_rank": 127,
      "surface_score": 1
    },
    "r2": {
      "elo_rank": 185,
      "age": 27.2,
      "elo": 1588.0,
      "hElo": 1545.9,
      "cElo": 1458.9,
      "gElo": 1528.8,
      "atp_rank": 188,
      "surface_score": 4
    },
    "c_elo1": 1629.7,
    "h_elo1": 1509.9,
    "c_elo2": 1458.9,
    "h_elo2": 1545.9,
    "ss1": 2,
    "ss2": 8,
    "prob1": 0.39275073025493024,
    "odds1": 2.55,
    "odds2": 1.65,
    "edge1": 0.0951,
    "edge2": -0.1561,
    "court_cpi": 37,
    "elo_found": true,
    "error": null,
    "status": "upcoming"
  },
  {
    "time": "",
    "player1": "Coria F.",
    "player2": "Bonding O.",
    "seed1": null,
    "seed2": null,
    "book_odds_home": 3.4,
    "book_odds_away": 1.3,
    "tournament": "Wimbledon",
    "surface": "grass",
    "category": "GS",
    "tour": "ATP",
    "elo_found": false,
    "error": "N/A: Bonding O.",
    "status": "upcoming"
  },
  {
    "time": "",
    "player1": "Kym J.",
    "player2": "Bueno G.",
    "seed1": null,
    "seed2": null,
    "book_odds_home": 1.19,
    "book_odds_away": 4.55,
    "tournament": "Wimbledon",
    "surface": "grass",
    "category": "GS",
    "tour": "ATP",
    "name1": "Jerome\u00a0Kym",
    "name2": "Gonzalo\u00a0Bueno",
    "r1": {
      "elo_rank": 178,
      "age": 23.2,
      "elo": 1601.0,
      "hElo": 1592.4,
      "cElo": 1541.0,
      "gElo": 1478.2,
      "atp_rank": 201,
      "surface_score": 4
    },
    "r2": {
      "elo_rank": 312,
      "age": 22.1,
      "elo": 1459.7,
      "hElo": 1298.4,
      "cElo": 1448.1,
      "gElo": 1429.8,
      "atp_rank": 183,
      "surface_score": 1
    },
    "c_elo1": 1541.0,
    "h_elo1": 1592.4,
    "c_elo2": 1448.1,
    "h_elo2": 1298.4,
    "ss1": 7,
    "ss2": 2,
    "prob1": 0.5692060997002572,
    "odds1": 1.76,
    "odds2": 2.32,
    "edge1": -0.2711,
    "edge2": 0.211,
    "court_cpi": 37,
    "elo_found": true,
    "error": null,
    "status": "upcoming"
  },
  {
    "time": "",
    "player1": "Broady L.",
    "player2": "Holmgren A.",
    "seed1": null,
    "seed2": 24,
    "book_odds_home": 2.14,
    "book_odds_away": 1.68,
    "tournament": "Wimbledon",
    "surface": "grass",
    "category": "GS",
    "tour": "ATP",
    "name1": "Liam\u00a0Broady",
    "name2": "August\u00a0Holmgren",
    "r1": {
      "elo_rank": 173,
      "age": 32.4,
      "elo": 1607.7,
      "hElo": 1585.8,
      "cElo": 1503.5,
      "gElo": 1516.9,
      "atp_rank": 209,
      "surface_score": 4
    },
    "r2": {
      "elo_rank": 219,
      "age": 28.0,
      "elo": 1549.1,
      "hElo": 1508.2,
      "cElo": 1465.3,
      "gElo": 1614.8,
      "atp_rank": 143,
      "surface_score": 4
    },
    "c_elo1": 1503.5,
    "h_elo1": 1585.8,
    "c_elo2": 1465.3,
    "h_elo2": 1508.2,
    "ss1": 8,
    "ss2": 7,
    "prob1": 0.36272467653150914,
    "odds1": 2.76,
    "odds2": 1.57,
    "edge1": -0.1046,
    "edge2": 0.042,
    "court_cpi": 37,
    "elo_found": true,
    "error": null,
    "status": "upcoming"
  },
  {
    "time": "",
    "player1": "Travaglia S.",
    "player2": "Mikrut L.",
    "seed1": 16,
    "seed2": null,
    "book_odds_home": 1.52,
    "book_odds_away": 2.46,
    "tournament": "Wimbledon",
    "surface": "grass",
    "category": "GS",
    "tour": "ATP",
    "name1": "Stefano\u00a0Travaglia",
    "name2": "Luka\u00a0Mikrut",
    "r1": {
      "elo_rank": 196,
      "age": 34.4,
      "elo": 1573.5,
      "hElo": 1540.6,
      "cElo": 1536.7,
      "gElo": 1453.7,
      "atp_rank": 132,
      "surface_score": 3
    },
    "r2": {
      "elo_rank": 166,
      "age": 22.1,
      "elo": 1618.5,
      "hElo": 1453.9,
      "cElo": 1643.0,
      "gElo": 1509.2,
      "atp_rank": 168,
      "surface_score": 1
    },
    "c_elo1": 1536.7,
    "h_elo1": 1540.6,
    "c_elo2": 1643.0,
    "h_elo2": 1453.9,
    "ss1": 5,
    "ss2": 1,
    "prob1": 0.4208015837400018,
    "odds1": 2.38,
    "odds2": 1.73,
    "edge1": -0.2371,
    "edge2": 0.1727,
    "court_cpi": 37,
    "elo_found": true,
    "error": null,
    "status": "upcoming"
  },
  {
    "time": "",
    "player1": "Den Ouden G.",
    "player2": "Zhou Y.",
    "seed1": null,
    "seed2": null,
    "book_odds_home": 2.25,
    "book_odds_away": 1.62,
    "tournament": "Wimbledon",
    "surface": "grass",
    "category": "GS",
    "tour": "ATP",
    "name1": "Guy\u00a0Den\u00a0Ouden",
    "name2": "Yi\u00a0Zhou",
    "r1": {
      "elo_rank": 269,
      "age": 24.1,
      "elo": 1502.0,
      "hElo": 1341.9,
      "cElo": 1494.3,
      "gElo": 1411.4,
      "atp_rank": 243,
      "surface_score": 1
    },
    "r2": {
      "elo_rank": 319,
      "age": 21.1,
      "elo": 1455.4,
      "hElo": 1444.6,
      "cElo": 1308.3,
      "gElo": 1427.7,
      "atp_rank": 253,
      "surface_score": 5
    },
    "c_elo1": 1494.3,
    "h_elo1": 1341.9,
    "c_elo2": 1308.3,
    "h_elo2": 1444.6,
    "ss1": 1,
    "ss2": 8,
    "prob1": 0.47655960953542786,
    "odds1": 2.1,
    "odds2": 1.91,
    "edge1": 0.0321,
    "edge2": -0.0938,
    "court_cpi": 37,
    "elo_found": true,
    "error": null,
    "status": "upcoming"
  },
  {
    "time": "15:30",
    "player1": "Schwaerzler J.",
    "player2": "O'Connell C.",
    "seed1": null,
    "seed2": 32,
    "book_odds_home": 4.56,
    "book_odds_away": 1.18,
    "tournament": "Wimbledon",
    "surface": "grass",
    "category": "GS",
    "tour": "ATP",
    "elo_found": false,
    "error": "N/A: O'Connell C.",
    "status": "upcoming"
  },
  {
    "time": "",
    "player1": "Rocha H.",
    "player2": "Mejia N.",
    "seed1": 9,
    "seed2": null,
    "book_odds_home": 1.29,
    "book_odds_away": 3.44,
    "tournament": "Wimbledon",
    "surface": "grass",
    "category": "GS",
    "tour": "ATP",
    "name1": "Henrique\u00a0Rocha",
    "name2": "Nicolas\u00a0Mejia",
    "r1": {
      "elo_rank": 114,
      "age": 22.1,
      "elo": 1690.3,
      "hElo": 1581.6,
      "cElo": 1673.0,
      "gElo": 1551.0,
      "atp_rank": 122,
      "surface_score": 2
    },
    "r2": {
      "elo_rank": 284,
      "age": 26.2,
      "elo": 1485.8,
      "hElo": 1428.2,
      "cElo": 1497.0,
      "gElo": 1442.9,
      "atp_rank": 164,
      "surface_score": 2
    },
    "c_elo1": 1673.0,
    "h_elo1": 1581.6,
    "c_elo2": 1497.0,
    "h_elo2": 1428.2,
    "ss1": 2,
    "ss2": 3,
    "prob1": 0.6507354714879554,
    "odds1": 1.54,
    "odds2": 2.86,
    "edge1": -0.1245,
    "edge2": 0.0586,
    "court_cpi": 37,
    "elo_found": true,
    "error": null,
    "status": "upcoming"
  },
  {
    "time": "",
    "player1": "Tseng C.",
    "player2": "Heide G.",
    "seed1": null,
    "seed2": null,
    "book_odds_home": 1.93,
    "book_odds_away": 1.82,
    "tournament": "Wimbledon",
    "surface": "grass",
    "category": "GS",
    "tour": "ATP",
    "name1": "Chun\u00a0Hsin\u00a0Tseng",
    "name2": "Gustavo\u00a0Heide",
    "r1": {
      "elo_rank": 214,
      "age": 24.8,
      "elo": 1555.7,
      "hElo": 1495.8,
      "cElo": 1542.7,
      "gElo": 1406.0,
      "atp_rank": 234,
      "surface_score": 2
    },
    "r2": {
      "elo_rank": 146,
      "age": 24.1,
      "elo": 1638.6,
      "hElo": 1507.4,
      "cElo": 1629.2,
      "gElo": 1488.8,
      "atp_rank": 187,
      "surface_score": 1
    },
    "c_elo1": 1542.7,
    "h_elo1": 1495.8,
    "c_elo2": 1629.2,
    "h_elo2": 1507.4,
    "ss1": 3,
    "ss2": 2,
    "prob1": 0.38304700819026105,
    "odds1": 2.61,
    "odds2": 1.62,
    "edge1": -0.1351,
    "edge2": 0.0675,
    "court_cpi": 37,
    "elo_found": true,
    "error": null,
    "status": "upcoming"
  },
  {
    "time": "",
    "player1": "Maestrelli F.",
    "player2": "Basing M.",
    "seed1": 10,
    "seed2": null,
    "book_odds_home": 1.54,
    "book_odds_away": 2.41,
    "tournament": "Wimbledon",
    "surface": "grass",
    "category": "GS",
    "tour": "ATP",
    "elo_found": false,
    "error": "N/A: Basing M.",
    "status": "upcoming"
  },
  {
    "time": "",
    "player1": "Gentzsch T.",
    "player2": "Kolar Z.",
    "seed1": null,
    "seed2": null,
    "book_odds_home": 1.47,
    "book_odds_away": 2.58,
    "tournament": "Wimbledon",
    "surface": "grass",
    "category": "GS",
    "tour": "ATP",
    "name1": "Tom\u00a0Gentzsch",
    "name2": "Zdenek\u00a0Kolar",
    "r1": {
      "elo_rank": 237,
      "age": 22.7,
      "elo": 1534.0,
      "hElo": 1476.4,
      "cElo": 1498.5,
      "gElo": 1447.9,
      "atp_rank": 228,
      "surface_score": 3
    },
    "r2": {
      "elo_rank": 270,
      "age": 29.6,
      "elo": 1501.5,
      "hElo": 1429.1,
      "cElo": 1488.3,
      "gElo": 1447.4,
      "atp_rank": 156,
      "surface_score": 2
    },
    "c_elo1": 1498.5,
    "h_elo1": 1476.4,
    "c_elo2": 1488.3,
    "h_elo2": 1429.1,
    "ss1": 4,
    "ss2": 3,
    "prob1": 0.5007195573448133,
    "odds1": 2.0,
    "odds2": 2.0,
    "edge1": -0.1796,
    "edge2": 0.1117,
    "court_cpi": 37,
    "elo_found": true,
    "error": null,
    "status": "upcoming"
  },
  {
    "time": "",
    "player1": "Draxl L.",
    "player2": "Bertola R.",
    "seed1": null,
    "seed2": null,
    "book_odds_home": 2.17,
    "book_odds_away": 1.65,
    "tournament": "Wimbledon",
    "surface": "grass",
    "category": "GS",
    "tour": "ATP",
    "name1": "Liam\u00a0Draxl",
    "name2": "Remy\u00a0Bertola",
    "r1": {
      "elo_rank": 184,
      "age": 24.4,
      "elo": 1588.7,
      "hElo": 1563.3,
      "cElo": 1496.0,
      "gElo": 1455.1,
      "atp_rank": 159,
      "surface_score": 4
    },
    "r2": {
      "elo_rank": 246,
      "age": 27.7,
      "elo": 1525.9,
      "hElo": 1501.2,
      "cElo": 1447.5,
      "gElo": 1463.0,
      "atp_rank": 197,
      "surface_score": 4
    },
    "c_elo1": 1496.0,
    "h_elo1": 1563.3,
    "c_elo2": 1447.5,
    "h_elo2": 1501.2,
    "ss1": 7,
    "ss2": 7,
    "prob1": 0.4886329450261501,
    "odds1": 2.05,
    "odds2": 1.96,
    "edge1": 0.0278,
    "edge2": -0.0947,
    "court_cpi": 37,
    "elo_found": true,
    "error": null,
    "status": "upcoming"
  },
  {
    "time": "",
    "player1": "Crawford O.",
    "player2": "Rodionov J.",
    "seed1": null,
    "seed2": 30,
    "book_odds_home": 3.1,
    "book_odds_away": 1.35,
    "tournament": "Wimbledon",
    "surface": "grass",
    "category": "GS",
    "tour": "ATP",
    "name1": "Oliver\u00a0Crawford",
    "name2": "Jurij\u00a0Rodionov",
    "r1": {
      "elo_rank": 337,
      "age": 26.9,
      "elo": 1438.5,
      "hElo": 1409.8,
      "cElo": 1373.0,
      "gElo": 1457.4,
      "atp_rank": 238,
      "surface_score": 3
    },
    "r2": {
      "elo_rank": 190,
      "age": 27.0,
      "elo": 1582.1,
      "hElo": 1557.0,
      "cElo": 1527.4,
      "gElo": 1511.8,
      "atp_rank": 152,
      "surface_score": 3
    },
    "c_elo1": 1373.0,
    "h_elo1": 1409.8,
    "c_elo2": 1527.4,
    "h_elo2": 1557.0,
    "ss1": 7,
    "ss2": 6,
    "prob1": 0.4223456627252684,
    "odds1": 2.37,
    "odds2": 1.73,
    "edge1": 0.0998,
    "edge2": -0.1631,
    "court_cpi": 37,
    "elo_found": true,
    "error": null,
    "status": "upcoming"
  },
  {
    "time": "",
    "player1": "Herbert P.",
    "player2": "Jubb P.",
    "seed1": null,
    "seed2": null,
    "book_odds_home": 1.65,
    "book_odds_away": 2.17,
    "tournament": "Wimbledon",
    "surface": "grass",
    "category": "GS",
    "tour": "ATP",
    "name1": "Pierre\u00a0Hugues\u00a0Herbert",
    "name2": "Paul\u00a0Jubb",
    "r1": {
      "elo_rank": 182,
      "age": 35.2,
      "elo": 1591.6,
      "hElo": 1568.9,
      "cElo": 1507.6,
      "gElo": 1556.7,
      "atp_rank": 249,
      "surface_score": 4
    },
    "r2": {
      "elo_rank": 356,
      "age": 26.4,
      "elo": 1425.8,
      "hElo": 1403.3,
      "cElo": 1338.0,
      "gElo": 1445.2,
      "atp_rank": 329,
      "surface_score": 4
    },
    "c_elo1": 1507.6,
    "h_elo1": 1568.9,
    "c_elo2": 1338.0,
    "h_elo2": 1403.3,
    "ss1": 7,
    "ss2": 7,
    "prob1": 0.6551705405623248,
    "odds1": 1.53,
    "odds2": 2.9,
    "edge1": 0.0491,
    "edge2": -0.116,
    "court_cpi": 37,
    "elo_found": true,
    "error": null,
    "status": "upcoming"
  },
  {
    "time": "",
    "player1": "Cecchinato M.",
    "player2": "Barrios Vera M.",
    "seed1": null,
    "seed2": 20,
    "book_odds_home": 5.97,
    "book_odds_away": 1.12,
    "tournament": "Wimbledon",
    "surface": "grass",
    "category": "GS",
    "tour": "ATP",
    "name1": "Marco\u00a0Cecchinato",
    "name2": "Tomas\u00a0Barrios\u00a0Vera",
    "r1": {
      "elo_rank": 207,
      "age": 33.6,
      "elo": 1564.5,
      "hElo": 1440.5,
      "cElo": 1535.0,
      "gElo": 1432.5,
      "atp_rank": 167,
      "surface_score": 2
    },
    "r2": {
      "elo_rank": 156,
      "age": 28.4,
      "elo": 1627.4,
      "hElo": 1558.5,
      "cElo": 1598.5,
      "gElo": 1581.9,
      "atp_rank": 137,
      "surface_score": 3
    },
    "c_elo1": 1535.0,
    "h_elo1": 1440.5,
    "c_elo2": 1598.5,
    "h_elo2": 1558.5,
    "ss1": 2,
    "ss2": 3,
    "prob1": 0.2973361005368109,
    "odds1": 3.36,
    "odds2": 1.42,
    "edge1": 0.1298,
    "edge2": -0.1902,
    "court_cpi": 37,
    "elo_found": true,
    "error": null,
    "status": "upcoming"
  },
  {
    "time": "",
    "player1": "McDonald M.",
    "player2": "Meligeni Rodrigues Alves F.",
    "seed1": 13,
    "seed2": null,
    "book_odds_home": 1.02,
    "book_odds_away": 13.79,
    "tournament": "Wimbledon",
    "surface": "grass",
    "category": "GS",
    "tour": "ATP",
    "elo_found": false,
    "error": "N/A: Meligeni Rodrigues Alves F.",
    "status": "upcoming"
  },
  {
    "time": "",
    "player1": "Ceban M.",
    "player2": "Carballes Baena R.",
    "seed1": null,
    "seed2": null,
    "book_odds_home": 6.75,
    "book_odds_away": 1.09,
    "tournament": "Wimbledon",
    "surface": "grass",
    "category": "GS",
    "tour": "ATP",
    "elo_found": false,
    "error": "N/A: Ceban M.",
    "status": "upcoming"
  },
  {
    "time": "",
    "player1": "Uchida K.",
    "player2": "Tomic B.",
    "seed1": null,
    "seed2": null,
    "book_odds_home": 4.22,
    "book_odds_away": 1.21,
    "tournament": "Wimbledon",
    "surface": "grass",
    "category": "GS",
    "tour": "ATP",
    "name1": "Kaichi\u00a0Uchida",
    "name2": "Bernard\u00a0Tomic",
    "r1": {
      "elo_rank": 419,
      "age": 31.6,
      "elo": 1360.2,
      "hElo": 1334.1,
      "cElo": 1308.0,
      "gElo": 1392.8,
      "atp_rank": 254,
      "surface_score": 3
    },
    "r2": {
      "elo_rank": 286,
      "age": 33.6,
      "elo": 1485.4,
      "hElo": 1446.7,
      "cElo": 1425.1,
      "gElo": 1513.2,
      "atp_rank": 192,
      "surface_score": 3
    },
    "c_elo1": 1308.0,
    "h_elo1": 1334.1,
    "c_elo2": 1425.1,
    "h_elo2": 1446.7,
    "ss1": 6,
    "ss2": 6,
    "prob1": 0.3333486818586164,
    "odds1": 3.0,
    "odds2": 1.5,
    "edge1": 0.0964,
    "edge2": -0.1598,
    "court_cpi": 37,
    "elo_found": true,
    "error": null,
    "status": "upcoming"
  },
  {
    "time": "",
    "player1": "Gaubas V.",
    "player2": "Mmoh M.",
    "seed1": 14,
    "seed2": null,
    "book_odds_home": 2.48,
    "book_odds_away": 1.52,
    "tournament": "Wimbledon",
    "surface": "grass",
    "category": "GS",
    "tour": "ATP",
    "name1": "Vilius\u00a0Gaubas",
    "name2": "Michael\u00a0Mmoh",
    "r1": {
      "elo_rank": 200,
      "age": 21.4,
      "elo": 1569.3,
      "hElo": 1553.7,
      "cElo": 1518.3,
      "gElo": 1523.4,
      "atp_rank": 129,
      "surface_score": 3
    },
    "r2": {
      "elo_rank": 160,
      "age": 28.3,
      "elo": 1622.8,
      "hElo": 1604.2,
      "cElo": 1513.1,
      "gElo": 1528.2,
      "atp_rank": 195,
      "surface_score": 4
    },
    "c_elo1": 1518.3,
    "h_elo1": 1553.7,
    "c_elo2": 1513.1,
    "h_elo2": 1604.2,
    "ss1": 7,
    "ss2": 8,
    "prob1": 0.49309268417804253,
    "odds1": 2.03,
    "odds2": 1.97,
    "edge1": 0.0899,
    "edge2": -0.151,
    "court_cpi": 37,
    "elo_found": true,
    "error": null,
    "status": "upcoming"
  },
  {
    "time": "",
    "player1": "Zhang Z.",
    "player2": "Searle H.",
    "seed1": null,
    "seed2": null,
    "book_odds_home": 1.65,
    "book_odds_away": 2.18,
    "tournament": "Wimbledon",
    "surface": "grass",
    "category": "GS",
    "tour": "ATP",
    "name1": "Zhizhen\u00a0Zhang",
    "name2": "Henry\u00a0Searle",
    "r1": {
      "elo_rank": 132,
      "age": 29.6,
      "elo": 1654.8,
      "hElo": 1628.5,
      "cElo": 1619.7,
      "gElo": 1603.9,
      "atp_rank": 189,
      "surface_score": 3
    },
    "r2": {
      "elo_rank": 421,
      "age": 20.1,
      "elo": 1357.4,
      "hElo": 1327.0,
      "cElo": 1296.8,
      "gElo": 1355.1,
      "atp_rank": 354,
      "surface_score": 3
    },
    "c_elo1": 1619.7,
    "h_elo1": 1628.5,
    "c_elo2": 1296.8,
    "h_elo2": 1327.0,
    "ss1": 5,
    "ss2": 7,
    "prob1": 0.8072451034020236,
    "odds1": 1.24,
    "odds2": 5.19,
    "edge1": 0.2012,
    "edge2": -0.266,
    "court_cpi": 37,
    "elo_found": true,
    "error": null,
    "status": "upcoming"
  },
  {
    "time": "",
    "player1": "Bax F.",
    "player2": "Rodesch C.",
    "seed1": null,
    "seed2": null,
    "book_odds_home": 6.57,
    "book_odds_away": 1.1,
    "tournament": "Wimbledon",
    "surface": "grass",
    "category": "GS",
    "tour": "ATP",
    "name1": "Florent\u00a0Bax",
    "name2": "Chris\u00a0Rodesch",
    "r1": {
      "elo_rank": 378,
      "age": 26.9,
      "elo": 1409.3,
      "hElo": 1392.1,
      "cElo": 1371.4,
      "gElo": 1404.7,
      "atp_rank": 256,
      "surface_score": 3
    },
    "r2": {
      "elo_rank": 135,
      "age": 24.7,
      "elo": 1651.5,
      "hElo": 1638.2,
      "cElo": 1570.2,
      "gElo": 1595.5,
      "atp_rank": 179,
      "surface_score": 4
    },
    "c_elo1": 1371.4,
    "h_elo1": 1392.1,
    "c_elo2": 1570.2,
    "h_elo2": 1638.2,
    "ss1": 6,
    "ss2": 7,
    "prob1": 0.2500523535245426,
    "odds1": 4.0,
    "odds2": 1.33,
    "edge1": 0.0978,
    "edge2": -0.1591,
    "court_cpi": 37,
    "elo_found": true,
    "error": null,
    "status": "upcoming"
  },
  {
    "time": "",
    "player1": "Neumayer L.",
    "player2": "Lajovic D.",
    "seed1": null,
    "seed2": 22,
    "book_odds_home": 1.93,
    "book_odds_away": 1.82,
    "tournament": "Wimbledon",
    "surface": "grass",
    "category": "GS",
    "tour": "ATP",
    "name1": "Lukas\u00a0Neumayer",
    "name2": "Dusan\u00a0Lajovic",
    "r1": {
      "elo_rank": 152,
      "age": 23.7,
      "elo": 1633.6,
      "hElo": 1486.6,
      "cElo": 1619.0,
      "gElo": 1472.4,
      "atp_rank": 165,
      "surface_score": 1
    },
    "r2": {
      "elo_rank": 154,
      "age": 35.9,
      "elo": 1628.1,
      "hElo": 1562.6,
      "cElo": 1597.6,
      "gElo": 1491.6,
      "atp_rank": 139,
      "surface_score": 3
    },
    "c_elo1": 1619.0,
    "h_elo1": 1486.6,
    "c_elo2": 1597.6,
    "h_elo2": 1562.6,
    "ss1": 2,
    "ss2": 3,
    "prob1": 0.47239707196412284,
    "odds1": 2.12,
    "odds2": 1.9,
    "edge1": -0.0457,
    "edge2": -0.0218,
    "court_cpi": 37,
    "elo_found": true,
    "error": null,
    "status": "upcoming"
  },
  {
    "time": "",
    "player1": "Tauson C.",
    "player2": "Shnaider D.",
    "seed1": null,
    "seed2": 7,
    "book_odds_home": 2.71,
    "book_odds_away": 1.45,
    "tournament": "Bad Homburg WTA",
    "surface": "grass",
    "category": "W500",
    "tour": "WTA",
    "name1": "Clara\u00a0Tauson",
    "name2": "Diana\u00a0Shnaider",
    "r1": {
      "elo_rank": 60,
      "age": 23.4,
      "elo": 1789.0,
      "hElo": 1768.7,
      "cElo": 1686.4,
      "gElo": 1634.6,
      "atp_rank": 23,
      "surface_score": 4
    },
    "r2": {
      "elo_rank": 16,
      "age": 22.1,
      "elo": 1929.9,
      "hElo": 1852.2,
      "cElo": 1860.3,
      "gElo": 1758.8,
      "atp_rank": 16,
      "surface_score": 3
    },
    "c_elo1": 1686.4,
    "h_elo1": 1768.7,
    "c_elo2": 1860.3,
    "h_elo2": 1852.2,
    "ss1": 8,
    "ss2": 5,
    "prob1": 0.32850540589258653,
    "odds1": 3.04,
    "odds2": 1.49,
    "edge1": -0.0405,
    "edge2": -0.0182,
    "court_cpi": 37,
    "elo_found": true,
    "error": null,
    "status": "upcoming"
  },
  {
    "time": "",
    "player1": "Jovic I.",
    "player2": "Wang X.",
    "seed1": 8,
    "seed2": null,
    "book_odds_home": 1.3,
    "book_odds_away": 3.46,
    "tournament": "Bad Homburg WTA",
    "surface": "grass",
    "category": "W500",
    "tour": "WTA",
    "name1": "Iva\u00a0Jovic",
    "name2": "Xiyu\u00a0Wang",
    "r1": {
      "elo_rank": 22,
      "age": 18.5,
      "elo": 1905.7,
      "hElo": 1847.4,
      "cElo": 1792.8,
      "gElo": 1797.8,
      "atp_rank": 17,
      "surface_score": 4
    },
    "r2": {
      "elo_rank": 76,
      "age": 25.1,
      "elo": 1748.9,
      "hElo": 1712.0,
      "cElo": 1700.8,
      "gElo": 1571.6,
      "atp_rank": 101,
      "surface_score": 3
    },
    "c_elo1": 1792.8,
    "h_elo1": 1847.4,
    "c_elo2": 1700.8,
    "h_elo2": 1712.0,
    "ss1": 7,
    "ss2": 6,
    "prob1": 0.7861901927670654,
    "odds1": 1.27,
    "odds2": 4.68,
    "edge1": 0.017,
    "edge2": -0.0752,
    "court_cpi": 37,
    "elo_found": true,
    "error": null,
    "status": "upcoming"
  },
  {
    "time": "",
    "player1": "Osaka N.",
    "player2": "Frech M.",
    "seed1": 6,
    "seed2": null,
    "book_odds_home": 1.28,
    "book_odds_away": 3.64,
    "tournament": "Bad Homburg WTA",
    "surface": "grass",
    "category": "W500",
    "tour": "WTA",
    "name1": "Naomi\u00a0Osaka",
    "name2": "Magdalena\u00a0Frech",
    "r1": {
      "elo_rank": 12,
      "age": 28.6,
      "elo": 1972.4,
      "hElo": 1913.9,
      "cElo": 1878.6,
      "gElo": 1741.1,
      "atp_rank": 15,
      "surface_score": 3
    },
    "r2": {
      "elo_rank": 83,
      "age": 28.4,
      "elo": 1738.2,
      "hElo": 1706.7,
      "cElo": 1654.2,
      "gElo": 1573.9,
      "atp_rank": 45,
      "surface_score": 4
    },
    "c_elo1": 1878.6,
    "h_elo1": 1913.9,
    "c_elo2": 1654.2,
    "h_elo2": 1706.7,
    "ss1": 7,
    "ss2": 7,
    "prob1": 0.7236181813555527,
    "odds1": 1.38,
    "odds2": 3.62,
    "edge1": -0.0576,
    "edge2": 0.0017,
    "court_cpi": 37,
    "elo_found": true,
    "error": null,
    "status": "upcoming"
  },
  {
    "time": "",
    "player1": "Kraus S.",
    "player2": "Kalinskaya A.",
    "seed1": null,
    "seed2": null,
    "book_odds_home": 2.86,
    "book_odds_away": 1.4,
    "tournament": "Bad Homburg WTA",
    "surface": "grass",
    "category": "W500",
    "tour": "WTA",
    "name1": "Sinja\u00a0Kraus",
    "name2": "Anna\u00a0Kalinskaya",
    "r1": {
      "elo_rank": 102,
      "age": 24.1,
      "elo": 1714.0,
      "hElo": 1633.7,
      "cElo": 1673.2,
      "gElo": 1544.1,
      "atp_rank": 92,
      "surface_score": 3
    },
    "r2": {
      "elo_rank": 18,
      "age": 27.4,
      "elo": 1921.5,
      "hElo": 1869.8,
      "cElo": 1811.6,
      "gElo": 1741.7,
      "atp_rank": 20,
      "surface_score": 4
    },
    "c_elo1": 1673.2,
    "h_elo1": 1633.7,
    "c_elo2": 1811.6,
    "h_elo2": 1869.8,
    "ss1": 3,
    "ss2": 7,
    "prob1": 0.24278388133096243,
    "odds1": 4.12,
    "odds2": 1.32,
    "edge1": -0.1069,
    "edge2": 0.0429,
    "court_cpi": 37,
    "elo_found": true,
    "error": null,
    "status": "upcoming"
  },
  {
    "time": "",
    "player1": "Sierra S.",
    "player2": "Zheng Q.",
    "seed1": null,
    "seed2": null,
    "book_odds_home": 2.9,
    "book_odds_away": 1.4,
    "tournament": "Bad Homburg WTA",
    "surface": "grass",
    "category": "W500",
    "tour": "WTA",
    "name1": "Solana\u00a0Sierra",
    "name2": "Qinwen\u00a0Zheng",
    "r1": {
      "elo_rank": 67,
      "age": 21.9,
      "elo": 1774.3,
      "hElo": 1652.9,
      "cElo": 1743.9,
      "gElo": 1617.5,
      "atp_rank": 58,
      "surface_score": 2
    },
    "r2": {
      "elo_rank": 28,
      "age": 23.6,
      "elo": 1865.5,
      "hElo": 1838.5,
      "cElo": 1818.0,
      "gElo": 1604.8,
      "atp_rank": 160,
      "surface_score": 3
    },
    "c_elo1": 1743.9,
    "h_elo1": 1652.9,
    "c_elo2": 1818.0,
    "h_elo2": 1838.5,
    "ss1": 2,
    "ss2": 6,
    "prob1": 0.5182686332875516,
    "odds1": 1.93,
    "odds2": 2.08,
    "edge1": 0.1734,
    "edge2": -0.2326,
    "court_cpi": 37,
    "elo_found": true,
    "error": null,
    "status": "upcoming"
  },
  {
    "time": "",
    "player1": "Williams V.",
    "player2": "Begu I.",
    "seed1": null,
    "seed2": null,
    "book_odds_home": 5.55,
    "book_odds_away": 1.14,
    "tournament": "Bad Homburg WTA",
    "surface": "grass",
    "category": "W500",
    "tour": "WTA",
    "elo_found": false,
    "error": "N/A: Begu I.",
    "status": "upcoming"
  },
  {
    "time": "",
    "player1": "Eala A.",
    "player2": "Mertens E.",
    "seed1": null,
    "seed2": null,
    "book_odds_home": 2.03,
    "book_odds_away": 1.77,
    "tournament": "Bad Homburg WTA",
    "surface": "grass",
    "category": "W500",
    "tour": "WTA",
    "name1": "Alexandra\u00a0Eala",
    "name2": "Elise\u00a0Mertens",
    "r1": {
      "elo_rank": 27,
      "age": 21.0,
      "elo": 1868.3,
      "hElo": 1819.3,
      "cElo": 1663.7,
      "gElo": 1782.7,
      "atp_rank": 35,
      "surface_score": 5
    },
    "r2": {
      "elo_rank": 23,
      "age": 30.5,
      "elo": 1898.2,
      "hElo": 1849.8,
      "cElo": 1813.1,
      "gElo": 1753.0,
      "atp_rank": 24,
      "surface_score": 3
    },
    "c_elo1": 1663.7,
    "h_elo1": 1819.3,
    "c_elo2": 1813.1,
    "h_elo2": 1849.8,
    "ss1": 9,
    "ss2": 7,
    "prob1": 0.54263792854284,
    "odds1": 1.84,
    "odds2": 2.19,
    "edge1": 0.05,
    "edge2": -0.1076,
    "court_cpi": 37,
    "elo_found": true,
    "error": null,
    "status": "upcoming"
  }
]